cnc/__init__.py
cnc/convert.py
ChineseNumberUtils-1.1.2.dist-info/LICENSE
ChineseNumberUtils-1.1.2.dist-info/METADATA
ChineseNumberUtils-1.1.2.dist-info/WHEEL
ChineseNumberUtils-1.1.2.dist-info/top_level.txt
ChineseNumberUtils-1.1.2.dist-info/RECORD
