Metadata-Version: 2.1
Name: ChineseNumberUtils
Version: 1.1.2
Summary: A simple converter between Chinese and arabic number
Home-page: https://github.com/nrchan/chinese-number-converter
Author: NR
Classifier: Programming Language :: Python :: 3
Classifier: Programming Language :: Python :: 3.6
Classifier: Programming Language :: Python :: 3.7
Classifier: Programming Language :: Python :: 3.8
Classifier: Programming Language :: Python :: 3.9
Classifier: Programming Language :: Python :: 3.10
Classifier: License :: OSI Approved :: MIT License
Classifier: Operating System :: OS Independent
Classifier: Natural Language :: Chinese (Traditional)
Classifier: Natural Language :: Chinese (Simplified)
Classifier: Topic :: Utilities
Requires-Python: >=3.6
License-File: LICENSE
